Metadata-Version: 2.1
Name: odoo-addon-mail_outbound_static
Version: 19.0.1.0.0.2
Requires-Dist: odoo==19.0.*
Summary: Allows you to configure the from header for a mail server.
Home-page: https://github.com/OCA/mail
License: LGPL-3
Author: braintec AG, LasLabs, Adhoc SA, Odoo Community Association (OCA)
Author-email: support@odoo-community.org
Classifier: Programming Language :: Python
Classifier: Framework :: Odoo
Classifier: Framework :: Odoo :: 19.0
Classifier: License :: OSI Approved :: GNU Lesser General Public License v3 (LGPLv3)
